pep517/__init__.py
pep517/build.py
pep517/check.py
pep517/colorlog.py
pep517/compat.py
pep517/dirtools.py
pep517/envbuild.py
pep517/meta.py
pep517/wrappers.py
pep517/in_process/__init__.py
pep517/in_process/_in_process.py
pep517-0.11.1.dist-info/LICENSE
pep517-0.11.1.dist-info/WHEEL
pep517-0.11.1.dist-info/METADATA
pep517-0.11.1.dist-info/RECORD
