Metadata-Version: 2.1
Name: pep517
Version: 0.11.1
Summary: Wrappers to build Python packages using PEP 517 hooks
Home-page: https://github.com/pypa/pep517
Author: Thomas Kluyver
Author-email: thomas@kluyver.me.uk
Classifier: License :: OSI Approved :: MIT License
Classifier: Programming Language :: Python :: 2.7
Classifier: Programming Language :: Python :: 3
Requires-Dist: toml;python_version<'3.6'
Requires-Dist: tomli >=1.1.0;python_version>='3.6'
Requires-Dist: importlib_metadata;python_version<'3.8'
Requires-Dist: zipp;python_version<'3.8'
